monoscope_pyramid/__init__.py
monoscope_pyramid-1.0.0.dist-info/METADATA
monoscope_pyramid-1.0.0.dist-info/WHEEL
monoscope_pyramid-1.0.0.dist-info/top_level.txt
monoscope_pyramid-1.0.0.dist-info/RECORD
