Metadata-Version: 2.1
Name: monoscope-pyramid
Version: 1.0.0
Summary: A Python Pyramid SDK for Monoscope integration
Author: Monoscope
Author-email: hello@apitoolkit.io
Requires-Dist: pyramid
Requires-Dist: monoscope-common
Requires-Dist: opentelemetry-api>=1.0.0
